{
  "命宮": {
    "紫微": "個性自我要求高,天生帶著領導氣場,重視面子與尊嚴,習慣站在主導的位置思考事情,不喜歡被人指揮。",
    "天機": "腦筋靈活,善於分析與應變,想法常常轉得比別人快,但也容易想太多、猶豫不決。",
    "太陽": "個性開朗直接,樂於付出照顧他人,有一種天生的熱情,但有時候太顧別人,容易忽略自己的需求。",
    "武曲": "個性務實剛毅,做事講求效率與結果,意志力強,不輕易妥協,但也可能顯得固執少了點彈性。",
    "天同": "個性溫和隨和,喜歡輕鬆自在的步調,不愛與人爭執,享受生活中的小確幸,但有時容易安於現狀。",
    "廉貞": "個性複雜多面,外表可能冷靜自持,內在情感其實很豐富,做事有原則,但情緒起伏也可能較大。",
    "天府": "個性穩重踏實,天生有一種包容力,善於理財與規劃,給人可靠的安全感,但有時保守求穩,不愛冒險。",
    "太陰": "個性細膩內斂,情感豐富且體貼,善於察言觀色,重視內心世界與家庭,但也容易多愁善感。",
    "貪狼": "個性多才多藝,興趣廣泛,交際手腕靈活,對新鮮事物充滿好奇心,但也容易三分鐘熱度。",
    "巨門": "口才犀利,善於分析深究,說話有自己的邏輯與見解,適合需要深入研究的領域,但也容易招惹口舌是非。",
    "天相": "個性溫和講原則,重視公平與協調,天生有服務他人的特質,做事謹慎細心,但有時候容易猶豫不決。",
    "天梁": "個性成熟穩重,天生帶有長輩緣,喜歡照顧與指導他人,重視原則與道德,但有時顯得固執己見。",
    "七殺": "個性剛強果斷,行動力十足,不怕挑戰與競爭,喜歡掌握主導權,但情緒也可能比較衝動直接。",
    "破軍": "個性獨立不受拘束,勇於打破常規、開創新局,適應變化的能力很強,但也容易衝動行事,不按牌理出牌。"
  },
  "命宮_空宮規則": {
    "說明": "命宮無主星時,以對宮(遷移宮)的主星來判斷個性特質,稱為「借星安命」",
    "開頭句": "命宮無主星,個性特質主要顯現在對外的應對與人生際遇上,需借對宮遷移宮的星曜來看。",
    "疊加邏輯": "抓遷移宮的主星,套用該星在『遷移宮』情境下的解釋,因為空宮命主的個性常常要在外在環境、際遇中才顯現出來",
    "結尾提醒句": "這類命格通常個性較有彈性,容易受環境影響而調整自己,也比較晚熟或需要透過歷練才能看清自己真正的樣貌。"
  },
  "兄弟宮": {
    "紫微": "手足或同儕中容易居於主導地位,彼此互動帶點尊卑感,但也可能因為主見強而有摩擦。",
    "天機": "手足間互動聰明機靈,常有交流想法的默契,但也可能因為想法太多而意見不合。",
    "太陽": "手足感情熱絡,容易扮演照顧或付出的一方,人緣好但也容易為手足操心。",
    "武曲": "手足互動較為理性務實,重視實質幫助勝過噓寒問暖,感情深但表達含蓄。",
    "天同": "手足相處輕鬆融洽,少有衝突,彼此感情溫和穩定。",
    "廉貞": "手足關係較複雜多變,情感深厚卻也可能有理念不合的緊張時刻。",
    "天府": "手足間互動穩重,常扮演照顧與協調的角色,關係穩固可靠。",
    "太陰": "手足感情細膩,容易與姊妹或女性手足特別親近,情感連結深。",
    "貪狼": "手足互動活潑多元,話題廣泛,但也可能各自忙碌、聚少離多。",
    "巨門": "手足間容易因言語溝通產生誤會或口角,需要多留意表達方式。",
    "天相": "手足相處講求公平和諧,常扮演調解的角色,關係平順。",
    "天梁": "手足中容易有一位扮演長輩型的照顧者角色,關係穩定有原則。",
    "七殺": "手足互動較為直接強烈,個性都鮮明,偶有競爭但也彼此欣賞。",
    "破軍": "手足關係變動性較大,各自個性獨立,感情深但相處模式不按牌理。"
  },
  "夫妻宮": {
    "紫微": "對伴侶的期待較高,容易被有領導特質或條件出眾的對象吸引,相處中也重視被尊重。",
    "天機": "與伴侶之間重視思想交流,喜歡能一起討論、腦力激盪的關係,但感情也容易多變。",
    "太陽": "對伴侶付出熱情,樂於照顧對方,但也容易在關係中扮演給予多於索取的一方。",
    "武曲": "感情表達較為務實含蓄,重視實際生活的共同經營,勝過浪漫言語。",
    "天同": "與伴侶相處步調輕鬆,重視情感中的舒適與陪伴,不喜歡爭執。",
    "廉貞": "感情豐富且強烈,容易陷入深刻的情感連結,但關係中也可能有較多起伏。",
    "天府": "對感情重視穩定與安全感,容易在關係中扮演可靠、顧全大局的一方。",
    "太陰": "感情細膩體貼,重視情感交流與陪伴的品質,容易被溫柔特質吸引。",
    "貪狼": "感情經營多采多姿,異性緣佳,喜歡有新鮮感的互動,但也需留意穩定度。",
    "巨門": "與伴侶溝通容易因言語產生誤解,建議多用溫和方式表達,避免因小事累積心結。",
    "天相": "重視感情中的公平與協調,善於顧慮對方感受,是體貼的伴侶類型。",
    "天梁": "在感情中容易扮演照顧、引導對方的角色,重視原則與責任感。",
    "七殺": "感情態度直接強烈,愛恨分明,喜歡主導感情走向。",
    "破軍": "感情經營較不受傳統框架拘束,重視新鮮感與自由度,關係變動性較高。"
  },
  "子女宮": {
    "紫微": "對子女或晚輩期待較高,教養風格傾向主導,重視他們的成就表現。",
    "天機": "與子女互動偏重思想交流,善於啟發他們的思考能力。",
    "太陽": "對子女付出照顧,關係熱絡,重視給予溫暖與支持。",
    "武曲": "教養風格務實嚴謹,重視紀律與實際能力的培養。",
    "天同": "與子女相處輕鬆愉快,重視溫馨和諧的親子氛圍。",
    "廉貞": "與子女的情感連結深厚但也可能情緒起伏,教養方式較具個人色彩。",
    "天府": "對子女照顧周到,善於規劃他們的未來,關係穩定可靠。",
    "太陰": "與子女情感細膩體貼,尤其容易與女兒或年幼子女特別親近。",
    "貪狼": "教養風格活潑多元,鼓勵子女多方發展興趣,但也需留意紀律拿捏。",
    "巨門": "與子女溝通需留意言語表達,容易因說話直接產生誤會。",
    "天相": "教養風格講求公平,重視協調親子之間的需求與界線。",
    "天梁": "對子女關愛中帶有原則,常扮演導師般的照顧角色。",
    "七殺": "教養風格較為嚴格直接,期待子女獨立自主、勇於面對挑戰。",
    "破軍": "教養方式不拘泥傳統,鼓勵子女打破框架,關係中變動性較高。"
  },
  "財帛宮": {
    "紫微": "對金錢有較高的掌控欲,重視理財的主導權,適合管理較大規模的財務。",
    "天機": "理財觀念靈活,善於分析投資機會,但也容易想法多變、難以決斷。",
    "太陽": "賺錢方式偏向付出型,樂於分享,但也要留意錢財容易因慷慨而流失。",
    "武曲": "財運穩健,理財態度務實謹慎,善於累積財富,是典型的財星。",
    "天同": "對金錢態度隨性知足,不特別汲汲營求,重視生活品質勝過累積財富。",
    "廉貞": "財運起伏較大,賺錢方式較有個人色彩,需留意衝動消費。",
    "天府": "理財能力佳,善於規劃與儲蓄,財運穩定,是庫藏之星。",
    "太陰": "財運偏向細水長流,善於精打細算,重視儲蓄與安全感。",
    "貪狼": "賺錢管道多元,善於交際帶來財路,但也容易有偏財傾向,需留意投機。",
    "巨門": "財運容易因言語或口舌糾紛而受影響,適合靠專業口才賺錢,例如顧問或教學。",
    "天相": "理財態度穩健公正,善於協調財務分配,不喜歡冒險投機。",
    "天梁": "財運穩定,善於長期規劃,也容易在關鍵時刻得到貴人財務上的幫助。",
    "七殺": "財運大起大落,賺錢方式積極進取,適合開創性強的事業累積財富。",
    "破軍": "財運變動性大,賺錢與花錢都較為果斷,需留意財務規劃的穩定性。"
  },
  "疾厄宮": {
    "紫微": "體質較穩定,但需留意壓力型的身心負擔,例如頭部或神經系統的緊繃。",
    "天機": "神經系統較為敏感,容易因思慮過多影響睡眠與情緒穩定度。",
    "太陽": "需留意心血管與眼睛的保養,也容易因過度付出而累積疲勞。",
    "武曲": "體質偏向剛強,但需留意呼吸系統或筋骨方面的保養。",
    "天同": "體質溫和,較少大病,但需留意因太過安逸而缺乏運動。",
    "廉貞": "需留意血液循環或情緒起伏帶來的身心影響。",
    "天府": "體質穩定,消化系統較需留意保養。",
    "太陰": "需留意婦科或內分泌相關的保養,情緒起伏也容易影響身體狀態。",
    "貪狼": "需留意肝腎與生活作息,容易因應酬頻繁影響健康。",
    "巨門": "需留意腸胃或口腔相關的保養,情緒壓力也容易反映在消化系統上。",
    "天相": "體質平穩,需留意泌尿系統的保養。",
    "天梁": "體質穩健,但需留意呼吸系統,年長後尤其要注意保養。",
    "七殺": "體質強健但容易因衝勁過度而忽略休息,需留意外傷風險。",
    "破軍": "體質變動性大,需留意過度勞累帶來的身體耗損。"
  },
  "遷移宮": {
    "紫微": "在外容易展現領導氣勢,受人尊重,外出發展運勢佳,適合往外闖蕩、擔任主導角色。",
    "天機": "在外反應靈活,善於隨機應變,適合經常變動、需要腦力思考的外務工作,但外出也容易勞心。",
    "太陽": "在外個性開朗大方,樂於助人,人緣廣闊,外出發展多能得貴人相助,但也容易為他人操心。",
    "武曲": "在外做事果決有魄力,行動力強,適合往外打拚事業,但待人接物可能顯得直接少些圓融。",
    "天同": "在外個性隨和好相處,外出運勢平穩,容易遇到輕鬆愉快的際遇,但也可能少了點衝勁去闖。",
    "廉貞": "在外表現較有個人色彩,善於交際應酬但內心保有自己的原則,外出際遇起伏可能較大。",
    "天府": "在外給人穩重可靠的印象,容易得到他人信任與提拔,外出發展平穩,善於累積資源與人脈。",
    "太陰": "在外個性溫和細膩,善於察言觀色,容易得到女性貴人或長輩緣,外出際遇偏向平和順遂。",
    "貪狼": "在外交際手腕靈活,善於應酬與拓展人脈,外出機會多元豐富,但也容易分心、見異思遷。",
    "巨門": "在外容易招惹口舌是非,需要多留意言語分寸,但也適合靠專業口才在外發展,例如需要溝通或分析的工作。",
    "天相": "在外重視形象與協調,善於處理人際之間的分寸,外出運勢平穩,容易扮演調解或輔助的角色。",
    "天梁": "在外容易得到長輩或貴人提攜,外出際遇偏向穩健,也適合擔任照顧、指導他人的角色。",
    "七殺": "在外行動力十足,勇於面對挑戰與競爭,外出發展容易大起大落,適合開創性強的工作環境。",
    "破軍": "在外適應變化能力強,勇於打破現狀、開創新局,外出際遇變動較大,適合需要開拓與革新的領域。"
  },
  "僕役宮": {
    "紫微": "朋友圈中容易居於領導地位,人脈資源豐富,但也需留意過於強勢影響友誼。",
    "天機": "朋友互動偏重思想交流,身邊常有聰明機靈的朋友,但情誼也可能較為多變。",
    "太陽": "朋友眾多且熱絡,樂於在朋友圈中付出與照顧他人。",
    "武曲": "朋友關係偏向實際互助,重視彼此在事務上的合作勝過情感交流。",
    "天同": "朋友相處輕鬆自在,交友圈氛圍和諧,少有衝突。",
    "廉貞": "朋友關係較為複雜多變,情誼深但也可能有理念不合的時候。",
    "天府": "朋友圈穩定,容易扮演讓人信賴依靠的角色。",
    "太陰": "朋友情誼細膩,容易與知心好友建立深厚情感連結。",
    "貪狼": "交友廣闊,社交手腕靈活,朋友圈多元豐富。",
    "巨門": "朋友相處需留意言語溝通,容易因口舌是非影響友誼。",
    "天相": "朋友圈重視公平和諧,常扮演調解人的角色。",
    "天梁": "朋友中容易有長輩型或提攜型的貴人存在。",
    "七殺": "朋友互動直接強烈,交情深但也可能因個性衝突產生摩擦。",
    "破軍": "朋友圈變動性較大,個性獨立,交友不受傳統框架侷限。"
  },
  "官祿宮": {
    "紫微": "適合擔任領導或管理職位,事業發展重視主導權與被尊重的成就感。",
    "天機": "適合需要靈活思考、分析規劃的工作,善於應變與策略發想。",
    "太陽": "適合需要與人互動、付出貢獻的工作,容易在服務他人中獲得成就感。",
    "武曲": "適合務實執行、講求效率成果的工作,例如財務或執行管理相關領域。",
    "天同": "適合步調穩定、氛圍和諧的工作環境,不喜歡高壓競爭的職場。",
    "廉貞": "適合需要個人特色發揮或帶點挑戰性的工作,事業起伏可能較大。",
    "天府": "適合需要穩健規劃、資源管理的工作,善於長期經營與累積。",
    "太陰": "適合需要細膩觀察、幕後規劃性質的工作,重視工作環境的安穩感。",
    "貪狼": "適合需要交際手腕、多元發展的工作,例如業務或公關領域。",
    "巨門": "適合需要專業口才與深度分析的工作,例如教學、諮詢或研究領域。",
    "天相": "適合需要協調溝通、講求公平原則的工作,例如行政或服務性質職務。",
    "天梁": "適合需要照顧他人、傳承指導的工作,例如教育或顧問性質領域。",
    "七殺": "適合具開創挑戰性質的工作,行動力強,適合衝刺型的事業發展。",
    "破軍": "適合需要創新突破、打破常規的工作,善於開創新局。"
  },
  "田宅宮": {
    "紫微": "重視居住環境的品質與格局,傾向擁有較具規模或象徵地位的產業。",
    "天機": "對居住環境的變動接受度較高,喜歡靈活調整生活空間。",
    "太陽": "重視家庭氛圍的溫暖,樂於為家人打造舒適的居住環境。",
    "武曲": "置產態度務實積極,善於規劃不動產累積,重視實質資產價值。",
    "天同": "對居住環境要求隨和,重視生活的舒適與安逸感。",
    "廉貞": "居住環境的變動性較大,對空間佈置有自己的個人風格與堅持。",
    "天府": "善於置產與累積不動產,居住環境穩定,重視安全感。",
    "太陰": "重視居家的細膩佈置與情感氛圍,容易對家有深厚的依戀。",
    "貪狼": "對居住環境喜歡多元變化,重視空間的美感與享受。",
    "巨門": "家庭成員間的溝通需多留意,避免言語摩擦影響家庭氣氛。",
    "天相": "重視家庭的和諧與公平,善於協調家人之間的需求。",
    "天梁": "居住環境穩定,容易在家中扮演照顧與主導的長輩角色。",
    "七殺": "置產態度較為積極大膽,居住環境變動性也可能較大。",
    "破軍": "對居住環境接受變動與革新,不特別戀舊,重視實用勝過傳統。"
  },
  "福德宮": {
    "紫微": "精神層面追求被肯定與尊重,享受生活品質,也重視自我價值感的實現。",
    "天機": "精神生活豐富,喜歡思考與學習新知,容易因想太多而影響心靈的平靜。",
    "太陽": "精神上樂於付出與貢獻,從幫助他人中獲得滿足感與快樂。",
    "武曲": "精神層面務實,享受透過努力累積成果帶來的踏實感。",
    "天同": "精神生活輕鬆知足,容易滿足於平淡簡單的幸福。",
    "廉貞": "精神世界豐富但也起伏較大,情感體驗深刻,需留意情緒調節。",
    "天府": "精神層面穩定安逸,善於為自己創造舒適安穩的生活品質。",
    "太陰": "精神生活細膩敏感,重視內心的平靜與情感的滋養。",
    "貪狼": "精神生活多采多姿,享受各種新鮮體驗帶來的樂趣。",
    "巨門": "精神層面容易多慮多疑,適合透過深度思考或研究找到心靈的出口。",
    "天相": "精神上追求平衡和諧,享受協調事物帶來的成就感。",
    "天梁": "精神層面成熟穩重,容易從照顧他人、傳承智慧中獲得滿足。",
    "七殺": "精神層面追求挑戰與突破,享受克服困難帶來的成就感。",
    "破軍": "精神世界獨立自由,享受打破常規、開創新局帶來的興奮感。"
  },
  "父母宮": {
    "紫微": "與父母或長輩的關係中,容易感受到權威或高標準的期待,彼此互動帶點尊卑距離。",
    "天機": "與父母互動偏重觀念交流,彼此想法可能有代溝但也能理性溝通。",
    "太陽": "與父親緣分較深厚,父母對自己付出關愛,關係熱絡溫暖。",
    "武曲": "與父母的相處較為理性務實,情感表達含蓄,重視實質的照顧與支持。",
    "天同": "與父母關係溫和融洽,家庭氛圍輕鬆,少有衝突。",
    "廉貞": "與父母的情感連結深厚但也可能有較多情緒起伏或理念不合。",
    "天府": "與父母關係穩定,容易獲得長輩的照顧與資源支持。",
    "太陰": "與母親緣分較深厚,情感細膩,重視與長輩之間的情感交流。",
    "貪狼": "與父母互動活潑但也可能較為疏離,各自有各自的生活重心。",
    "巨門": "與父母溝通需留意言語表達,容易因話語直接產生誤會或摩擦。",
    "天相": "與父母關係講求公平和諧,常扮演調解家庭關係的角色。",
    "天梁": "與父母或長輩緣分深厚,容易得到他們的指導與提攜。",
    "七殺": "與父母的相處較為直接強烈,彼此個性都鮮明,可能有較多意見衝突。",
    "破軍": "與父母的關係較為獨立疏離,價值觀差異可能較大,但情感底層仍深。"
  },
  "四化疊加": {
    "化祿": "在原本的特質上,增添順遂、人緣加分的色彩。",
    "化權": "在原本的特質上,增添掌控欲與爆發力,但也可能顯得強勢。",
    "化科": "在原本的特質上,增添文書、名聲、貴人運。",
    "化忌": "在原本的特質上,提醒需要留意的糾結或阻礙課題。"
  },
  "亮度疊加": {
    "說明": "廟旺得利平不陷七階會先收斂成廟/旺/平/陷四個等級再套用下面的文字(得→旺、利→平、不→陷),所以同一句文字可能對應到不只一個原始等級,這是正常的,不是bug。",
    "廟": "這裡的特質會發揮到最完整、最有力的狀態,是這顆星在這個位置很理想的狀況,可以放心倚重這方面的特質。",
    "旺": "這裡的特質可以穩定發揮,不容易忽強忽弱,平常怎麼表現大概就會怎麼呈現。",
    "平": "這裡的特質中規中矩,沒有特別加分,也沒有明顯扣分,平平淡淡地發揮基本作用就好。",
    "陷": "這裡的特質比較發揮不出來,容易打折扣、卡卡的,是這個宮位裡比較需要多留意、多花點心力去補強的地方,而不是完全不管它。"
  },
  "亮度原始等級白話": {
    "說明": "紫微斗數的星曜亮度分廟旺得利平不陷七階,數值愈前面愈強。這裡對應到每一階給一個白話說明,組句時會寫成「{星名}的亮度是{原始等級}({白話})」,不要只丟一個單字讓使用者猜。",
    "廟": "最強的等級",
    "旺": "偏強的等級",
    "得": "中上的等級",
    "利": "中間偏弱一點的等級",
    "平": "中間的等級",
    "不": "偏弱的等級",
    "陷": "最弱的等級"
  }
}